deepsource/__init__.py
deepsource/__main__.py
deepsource/celery_app.py
deepsource/bin/__init__.py
deepsource/bin/deepsource.py
deepsource/exceptions/__init__.py
deepsource/exceptions/base.py
deepsource/exceptions/parsing.py
deepsource/parse/__init__.py
deepsource/parse/aawait.py
deepsource/parse/assign.py
deepsource/parse/attribute.py
deepsource/parse/binop.py
deepsource/parse/boolop.py
deepsource/parse/call.py
deepsource/parse/compare.py
deepsource/parse/constant.py
deepsource/parse/ddict.py
deepsource/parse/formatted_value.py
deepsource/parse/genexp.py
deepsource/parse/imports.py
deepsource/parse/joined_str.py
deepsource/parse/listcomp.py
deepsource/parse/llist.py
deepsource/parse/name.py
deepsource/parse/slice.py
deepsource/parse/subscript.py
deepsource/parse/syntax.py
deepsource/parse/ttuple.py
deepsource/patterns/__init__.py
deepsource/patterns/code_generation/__init__.py
deepsource/patterns/code_injection/__init__.py
deepsource/patterns/code_injection/pickle.py
deepsource/patterns/code_injection/shlex.py
deepsource/patterns/command_execution/__init__.py
deepsource/patterns/command_execution/os_system.py
deepsource/patterns/command_execution/subprocess.py
deepsource/patterns/compiled_code/__init__.py
deepsource/patterns/directory_traversal/__init__.py
deepsource/patterns/importing/__init__.py
deepsource/patterns/networking/__init__.py
deepsource/patterns/sql_injection/__init__.py
deepsource/patterns/string_manipulation/__init__.py
deepsource/tasks/__init__.py
deepsource/tasks/base.py
deepsource/tasks/scan_file.py
deepsource/util/__init__.py
deepsource/util/file_operations/__init__.py
deepsource-0.1.2.dist-info/LICENSE
deepsource-0.1.2.dist-info/METADATA
deepsource-0.1.2.dist-info/WHEEL
deepsource-0.1.2.dist-info/top_level.txt
deepsource-0.1.2.dist-info/RECORD
