Metadata-Version: 2.1
Name: deepsource
Version: 0.1.2
Summary: A python scanner, work in progress...
Home-page: https://github.com/BillSchumacher/deepsource
Author: Bill Schumacher
Author-email: william.schumacher@gmail.com
License: MIT
Classifier: License :: OSI Approved :: MIT License
Classifier: Programming Language :: Python
Classifier: Programming Language :: Python :: 3.10
Classifier: Topic :: Security
License-File: LICENSE
Requires-Dist: celery
Requires-Dist: redis
